{
  "mlb_units": -1.36,
  "record": {
    "w": 3,
    "l": 4,
    "push": 0
  },
  "by_tag": {
    "NEUTRAL": {
      "w": 3,
      "l": 4,
      "units": -1.36
    }
  },
  "by_stars": {
    "3": {
      "w": 1,
      "l": 2,
      "units": -1.1
    },
    "4": {
      "w": 1,
      "l": 1,
      "units": -0.18
    },
    "2": {
      "w": 1,
      "l": 2,
      "units": -1.08
    }
  },
  "totals_units": -1.0,
  "totals_record": {
    "w": 0,
    "l": 1,
    "push": 0
  },
  "parlay_legs": {
    "w": 1,
    "l": 0
  },
  "history": [
    {
      "graded_at": "2026-07-19T00:34:51.223860+00:00",
      "w": 3,
      "l": 5,
      "units": -2.36
    }
  ]
}